xgit/__init__.py
xgit/__main__.py
xgit/gitignore/dart.gitignore
xgit/gitignore/global.gitignore
xgit/gitignore/jvm.gitignore
xgit/gitignore/py.gitignore
xgit/utils.py
xgit-0.1.5.dist-info/entry_points.txt
xgit-0.1.5.dist-info/LICENSE
xgit-0.1.5.dist-info/WHEEL
xgit-0.1.5.dist-info/METADATA
xgit-0.1.5.dist-info/RECORD
