Metadata-Version: 2.1
Name: xgit
Version: 0.1.5
Summary: An opinionated command line tools to make your life easier with Git and Gitignore
Home-page: https://github.com/patarapolw/xgit
License: MIT
Keywords: git
Author: Pacharapol Withayasakpunt
Author-email: patarapolw@gmail.com
Requires-Python: >=3.5,<4.0
Classifier: License :: OSI Approved :: MIT License
Classifier: Programming Language :: Python :: 3
Classifier: Programming Language :: Python :: 3.5
Classifier: Programming Language :: Python :: 3.6
Classifier: Programming Language :: Python :: 3.7
Requires-Dist: requests (>=2.21,<3.0)
Project-URL: Repository, https://github.com/patarapolw/xgit
